glovar/__init__.py
glovar/glovar.py
glovar-0.2.2.dist-info/METADATA
glovar-0.2.2.dist-info/WHEEL
glovar-0.2.2.dist-info/top_level.txt
glovar-0.2.2.dist-info/RECORD
