Metadata-Version: 2.1
Name: glovar
Version: 0.2.2
Summary: A package for managing JSON-based global variables by file context.
Home-page: https://github.com/PaceGG/Python-Global-vars-lib
Author: PaceGG
Author-email: yura3012004@gmail.com
Classifier: Programming Language :: Python :: 3
Classifier: License :: OSI Approved :: MIT License
Classifier: Operating System :: OS Independent
Requires-Python: >=3.6
